{
  "last_updated": "2026-05-30T12:06:44.469667",
  "total_rates": 287,
  "total_lenders": 34,
  "scrapers_run": 34,
  "scrapers_successful": 34,
  "scrapers_failed": 0,
  "lenders": [
    "alterna",
    "atb",
    "bmo",
    "butlermortgage",
    "centum",
    "cibc",
    "cmls",
    "coastcapital",
    "cwb",
    "desjardins",
    "eqbank",
    "equitable",
    "firstnational",
    "hometrust",
    "intellimortgage",
    "laurentian",
    "lendwise",
    "manulife",
    "mcap",
    "meridian",
    "merix",
    "motive",
    "nationalbank",
    "nesto",
    "rbc",
    "rfa",
    "scotiabank",
    "simplii",
    "streetcapital",
    "tangerine",
    "td",
    "truenorth",
    "vancity",
    "wealthsimple"
  ],
  "scraper_results": [
    {
      "lender": "rbc",
      "success": true,
      "rates_found": 29,
      "duration": 4.457813501358032,
      "error": null
    },
    {
      "lender": "td",
      "success": true,
      "rates_found": 15,
      "duration": 11.28682804107666,
      "error": null
    },
    {
      "lender": "bmo",
      "success": true,
      "rates_found": 6,
      "duration": 0.5147454738616943,
      "error": null
    },
    {
      "lender": "scotiabank",
      "success": true,
      "rates_found": 12,
      "duration": 30.456995010375977,
      "error": null
    },
    {
      "lender": "cibc",
      "success": true,
      "rates_found": 8,
      "duration": 0.5169057846069336,
      "error": null
    },
    {
      "lender": "nationalbank",
      "success": true,
      "rates_found": 3,
      "duration": 8.64795708656311,
      "error": null
    },
    {
      "lender": "nesto",
      "success": true,
      "rates_found": 4,
      "duration": 4.118264675140381,
      "error": null
    },
    {
      "lender": "tangerine",
      "success": true,
      "rates_found": 8,
      "duration": 30.485674619674683,
      "error": null
    },
    {
      "lender": "eqbank",
      "success": true,
      "rates_found": 8,
      "duration": 6.150493860244751,
      "error": null
    },
    {
      "lender": "simplii",
      "success": true,
      "rates_found": 8,
      "duration": 30.41340661048889,
      "error": null
    },
    {
      "lender": "motive",
      "success": true,
      "rates_found": 8,
      "duration": 9.810929298400879,
      "error": null
    },
    {
      "lender": "alterna",
      "success": true,
      "rates_found": 8,
      "duration": 7.8829052448272705,
      "error": null
    },
    {
      "lender": "wealthsimple",
      "success": true,
      "rates_found": 3,
      "duration": 8.50619101524353,
      "error": null
    },
    {
      "lender": "meridian",
      "success": true,
      "rates_found": 8,
      "duration": 30.43820881843567,
      "error": null
    },
    {
      "lender": "desjardins",
      "success": true,
      "rates_found": 6,
      "duration": 4.827832937240601,
      "error": null
    },
    {
      "lender": "vancity",
      "success": true,
      "rates_found": 7,
      "duration": 3.2100002765655518,
      "error": null
    },
    {
      "lender": "coastcapital",
      "success": true,
      "rates_found": 5,
      "duration": 6.1298699378967285,
      "error": null
    },
    {
      "lender": "atb",
      "success": true,
      "rates_found": 8,
      "duration": 5.6602301597595215,
      "error": null
    },
    {
      "lender": "cwb",
      "success": true,
      "rates_found": 6,
      "duration": 10.377258777618408,
      "error": null
    },
    {
      "lender": "firstnational",
      "success": true,
      "rates_found": 9,
      "duration": 4.12976336479187,
      "error": null
    },
    {
      "lender": "mcap",
      "success": true,
      "rates_found": 8,
      "duration": 4.397078990936279,
      "error": null
    },
    {
      "lender": "laurentian",
      "success": true,
      "rates_found": 8,
      "duration": 6.131726026535034,
      "error": null
    },
    {
      "lender": "manulife",
      "success": true,
      "rates_found": 8,
      "duration": 4.851891756057739,
      "error": null
    },
    {
      "lender": "rfa",
      "success": true,
      "rates_found": 8,
      "duration": 22.357677698135376,
      "error": null
    },
    {
      "lender": "cmls",
      "success": true,
      "rates_found": 8,
      "duration": 3.7970871925354004,
      "error": null
    },
    {
      "lender": "merix",
      "success": true,
      "rates_found": 8,
      "duration": 4.044473171234131,
      "error": null
    },
    {
      "lender": "lendwise",
      "success": true,
      "rates_found": 7,
      "duration": 6.849179029464722,
      "error": null
    },
    {
      "lender": "butlermortgage",
      "success": true,
      "rates_found": 14,
      "duration": 5.576101303100586,
      "error": null
    },
    {
      "lender": "intellimortgage",
      "success": true,
      "rates_found": 6,
      "duration": 30.426838636398315,
      "error": null
    },
    {
      "lender": "streetcapital",
      "success": true,
      "rates_found": 8,
      "duration": 3.3027660846710205,
      "error": null
    },
    {
      "lender": "centum",
      "success": true,
      "rates_found": 6,
      "duration": 5.687802791595459,
      "error": null
    },
    {
      "lender": "truenorth",
      "success": true,
      "rates_found": 16,
      "duration": 10.517194032669067,
      "error": null
    },
    {
      "lender": "equitable",
      "success": true,
      "rates_found": 7,
      "duration": 5.971311807632446,
      "error": null
    },
    {
      "lender": "hometrust",
      "success": true,
      "rates_found": 6,
      "duration": 30.439921379089355,
      "error": null
    }
  ]
}